cisco_opentelemetry_specifications/__init__.py
cisco_opentelemetry_specifications/consts.py
cisco_opentelemetry_specifications/payload_attributes.py
cisco_opentelemetry_specifications/semantic_attributes.py
cisco_opentelemetry_specifications-0.0.23.dist-info/WHEEL
cisco_opentelemetry_specifications-0.0.23.dist-info/METADATA
cisco_opentelemetry_specifications-0.0.23.dist-info/RECORD
